[
    {
        "descTextMapHash": 3157102895,
        "guideQuestId": 40040,
        "guides": [
            "GuideProjectionGameRotationXYpc",
            "GuideProjectionGameRotationXYios",
            "GuideProjectionGameRotationXYps4",
            "GuideProjectionGameRotationZpc",
            "GuideProjectionGameRotationZios",
            "GuideProjectionGameRotationZps4",
            "GuideProjectionGameSwitchpc",
            "GuideProjectionGameSwitchios",
            "GuideProjectionGameSwitchps4"
        ],
        "leadGuides": [
            "GuideProjectionGameRotationXYpc",
            "GuideProjectionGameRotationXYios",
            "GuideProjectionGameRotationXYps4"
        ],
        "nameTextMapHash": 1376840672,
        "pushTipsIdJoypad": 11019,
        "pushTipsIdMouse": 11021,
        "pushTipsIdTouch": 11020,
        "scheduleId": 2010001,
        "sensitivityFreeRotation": 180.0,
        "sensitivityFreeRotationJoypad": 2.0,
        "sensitivitySingleAxisRotation": 180.0,
        "sensitivitySingleAxisRotationJoypad": 4.0,
        "sensitivitySingleAxisTranslation": 5.0,
        "sensitivitySingleAxisTranslationJoypad": 0.029999999329447746,
        "timeThresholdShowContinuousProgress": 120,
        "timeThresholdShowStandbyPrompt": 10,
        "timeThresholdUnlockAnswer": 120
    }
]